<?xml version="1.0" encoding="us-ascii"?>
<SetupComponentInfo Name="Client Access PreSetup" DescriptionId="SetupComponentPreSetupClientAccess">

  <ServerTasks>

    <ServerTaskInfo Id="_584ca75c512643a388eaea191c884bbf" Component="EXCHANGE14:\Current\Release\Shared\Datacenter\Setup">
      <Install />

      <!-- Only upgrade mode is used by the binding tasks-->
      <BuildToBuildUpgrade>
        <Standalone></Standalone>
      </BuildToBuildUpgrade>

      <DisasterRecovery />
      <Uninstall />
    </ServerTaskInfo>

  </ServerTasks>

</SetupComponentInfo>

